README.md
setup.py
amantadine/__init__.py
amantadine/pages.py
amantadine/project.py
amantadine/record.py
amantadine/render.py
amantadine.egg-info/PKG-INFO
amantadine.egg-info/SOURCES.txt
amantadine.egg-info/dependency_links.txt
amantadine.egg-info/top_level.txt
example/__init__.py
example/base.py
example/main.py
example/src/__init__.py
example/src/hello.py