Metadata-Version: 2.1
Name: amantadine
Version: 0.0.4
Summary: Amantadine is a framework for rendering HTML on the server
Home-page: https://github.com/isclub/amantadine
License: MIT License
Platform: UNKNOWN
